[
  {
    "chapter_num": 0,
    "title": "Introduction",
    "url": "https://automatetheboringstuff.com/3e/chapter0.html"
  },
  {
    "chapter_num": 1,
    "title": "Chapter 1 - Python Basics",
    "url": "https://automatetheboringstuff.com/3e/chapter1.html"
  },
  {
    "chapter_num": 2,
    "title": "Chapter 2 - if-else and Flow Control",
    "url": "https://automatetheboringstuff.com/3e/chapter2.html"
  },
  {
    "chapter_num": 3,
    "title": "Chapter 3 - Loops",
    "url": "https://automatetheboringstuff.com/3e/chapter3.html"
  },
  {
    "chapter_num": 4,
    "title": "Chapter 4 - Functions",
    "url": "https://automatetheboringstuff.com/3e/chapter4.html"
  },
  {
    "chapter_num": 5,
    "title": "Chapter 5 - Debugging",
    "url": "https://automatetheboringstuff.com/3e/chapter5.html"
  },
  {
    "chapter_num": 6,
    "title": "Chapter 6 - Lists",
    "url": "https://automatetheboringstuff.com/3e/chapter6.html"
  },
  {
    "chapter_num": 7,
    "title": "Chapter 7 - Dictionaries and Structuring Data",
    "url": "https://automatetheboringstuff.com/3e/chapter7.html"
  },
  {
    "chapter_num": 8,
    "title": "Chapter 8 - Strings and Text Editing",
    "url": "https://automatetheboringstuff.com/3e/chapter8.html"
  },
  {
    "chapter_num": 9,
    "title": "Chapter 9 - Text Pattern Matching with Regular Expressions",
    "url": "https://automatetheboringstuff.com/3e/chapter9.html"
  },
  {
    "chapter_num": 10,
    "title": "Chapter 10 - Reading and Writing Files",
    "url": "https://automatetheboringstuff.com/3e/chapter10.html"
  },
  {
    "chapter_num": 11,
    "title": "Chapter 11 - Organizing Files",
    "url": "https://automatetheboringstuff.com/3e/chapter11.html"
  },
  {
    "chapter_num": 12,
    "title": "Chapter 12 - Designing and Deploying Command Line Programs",
    "url": "https://automatetheboringstuff.com/3e/chapter12.html"
  },
  {
    "chapter_num": 13,
    "title": "Chapter 13 - Web Scraping",
    "url": "https://automatetheboringstuff.com/3e/chapter13.html"
  },
  {
    "chapter_num": 14,
    "title": "Chapter 14 - Excel Spreadsheets",
    "url": "https://automatetheboringstuff.com/3e/chapter14.html"
  },
  {
    "chapter_num": 15,
    "title": "Chapter 15 - Google Sheets",
    "url": "https://automatetheboringstuff.com/3e/chapter15.html"
  },
  {
    "chapter_num": 16,
    "title": "Chapter 16 - SQLite Databases",
    "url": "https://automatetheboringstuff.com/3e/chapter16.html"
  },
  {
    "chapter_num": 17,
    "title": "Chapter 17 - PDF and Word Documents",
    "url": "https://automatetheboringstuff.com/3e/chapter17.html"
  },
  {
    "chapter_num": 18,
    "title": "Chapter 18 - CSV, JSON, and XML Files",
    "url": "https://automatetheboringstuff.com/3e/chapter18.html"
  },
  {
    "chapter_num": 19,
    "title": "Chapter 19 - Keeping Time, Scheduling Tasks, and Launching Programs",
    "url": "https://automatetheboringstuff.com/3e/chapter19.html"
  },
  {
    "chapter_num": 20,
    "title": "Chapter 20 - Sending Email, Texts, and Push Notifications",
    "url": "https://automatetheboringstuff.com/3e/chapter20.html"
  },
  {
    "chapter_num": 21,
    "title": "Chapter 21 - Making Graphs and Manipulating Images",
    "url": "https://automatetheboringstuff.com/3e/chapter21.html"
  },
  {
    "chapter_num": 22,
    "title": "Chapter 22 - Recognizing Text in Images",
    "url": "https://automatetheboringstuff.com/3e/chapter22.html"
  },
  {
    "chapter_num": 23,
    "title": "Chapter 23 - Controlling the Keyboard and Mouse",
    "url": "https://automatetheboringstuff.com/3e/chapter23.html"
  },
  {
    "chapter_num": 24,
    "title": "Chapter 24 - Text-to-Speech and Speech Recognition Engines",
    "url": "https://automatetheboringstuff.com/3e/chapter24.html"
  }
]